[{"Escayolar": ["Enyesar, inmovilizar por medio de un vendaje de yeso o de escayola un miembro roto, dislocado, etc.", 12], "Discernir": ["Distinguir una cosa de otra", 8], "Arremolinarse": ["Formarse remolinos.", 1], "Borrasca": ["Alteraci\u00f3n atmosf\u00e9tica caracterizada por viento y lluvia que se produce por bajas presiones.", 16], "Traqueteo": ["Ruido de un coche", 8], "destartalado": ["roto - para coches", 4], "Hiedra": ["Planta trepadora por otras plantas", 5], "Tra\u00edlla": ["Cuerda o correa con que se lleva al perro", 6]}, {"Throttling": ["Estrangulaci\u00f3n", 1], "Catalys": ["Catalizadores", 0], "Undergoes": ["Sufre", 0], "Tombstone": ["L\u00e1pida", 1], "You have to fuss": ["Tienes que preocuparte", 0], "Tittled": ["Inclinado", 4], "By the same token": ["De la misma manera", 6], "carved": ["tallado", 1], "seeping": ["filtr\u00e1ndose", 1], "The latter theorem": ["El \u00faltimo teorema", 2], "whence": ["de donde", 1], "smooth": ["suave", 1], "Dashed": ["Punteado", 3], "sake": ["motivo", 2], "readily": ["f\u00e1cilmente", 1], "Undergoin": ["Sufriendo", 1], "Undergoing": ["sufriendo", 3], "Pump": ["bomba", 1], "Acknoledges": ["reconoce", 5], "chamber": ["c\u00e1mara", 5], "Bundled": ["Empaquetado", 2], "Flawed": ["defectuoso", 2], "Closely wound turns": ["Vueltas estrechamente enrolladas", 4], "Thereof": ["del mismo", 3], "Glance": ["mirada", 2], "Suitable": ["apropiado", 4], "Handled": ["manejado", 2], "Astonishing": ["Asombroso", 2], "Windings": ["devanados", 1], "Refinement": ["refinamiento", 5], "Inherits": ["Hereda", 1], "Foil": ["Fustrar", 2], "As quoted": ["seg\u00fan lo citado", 2], "Piecewise": ["por partes", 2], "Fruifully": ["Fructifero", 0], "cast into": ["echado en", 0], "namely": ["a saber", 2], "Reject the latter on physical grounds": ["Rechazar este \u00faltimo por razones f\u00edsicas", 0], "Arise later": ["Surgir m\u00e1s tarde", 0], "Twofold": ["Doble", 4], "Herein": ["En este documento", 3], "Gratings": ["Rejillas", 1], "Couplers": ["Acopladores", 1], "splitter ": ["divisor", 1], "Review": ["Rese\u00f1a", 0], "Hints": ["Consejos", 1], "Lenses": ["Lentes", 1], "Ease": ["Facilitar", 0], "Aforementioned": ["Ya mencionado", 1], "Besides": ["Adem\u00e1s", 0], "Locus": ["Lugar", 0], "Negligible": ["Despreciable", 0], "Overkill": ["Exagerar", 0], "Enforced": ["Forzado", 0], "Whichever": ["La que sea", 0], "Delightful": ["Exquisito", 0], "well": ["pozo", 1], "narrow": ["angosto", 0], "Strikingly": ["Sorprendentemente", 0], "Reminiscent": ["Evocar recuerdos", 1], "Subtle": ["Sutil", 0], "Burden": ["Carga", 0], "Nearby": ["Cercano", 1], "Subsumes": ["Incluye", 0], "Underlying": ["Subyacente", 0], "Overview": ["Visi\u00f3n general", 1], "In this regard": ["En este aspecto", 0], "Overcomes": ["Supera", 0], "Over abroad": ["En el extranjero", 0], "The best of our knoledges": ["Hasta donde sabemos", 0], "Overlooked": ["Pasado por alto", 0], "Squeezer": ["Exprimidor", 1], "Regarding": ["Con respecto a", 0], "Cladding": ["Recubrimiento", 0], "Insights": ["Perspectivas", 0], "Twist": ["Girar", 0], "Coupling": ["Acoplamiento", 0], "Spliced": ["Empalmado", 0], "Overlap": ["Tranlapar", 0], "Enhance": ["Intensificar", 0], "Tapering": ["Estrech\u00e1ndose", 0], "Etching": ["Grabado", 0], "Customized": ["Personalizado", 0], "subtle": ["sutil", 0], "commit": ["comprometerse", 0], "doubt": ["duda", 0], "overall": ["general", 0], "the latter": ["el \u00faltimo", 0], "Hits": ["Golpes", 0], "Ther fomrer": ["The former", 0], "El primero": ["Neatly", 0], "Esmeradamente": ["s", 0], "The former": ["El primerp", 0], "Ther former": ["El primero", 0], "Neatly": ["Esmeradamente", 0]}]